realized_library/__init__.py
realized_library/config.py
realized_library/_utils/__init__.py
realized_library/_utils/derivative_approximation.py
realized_library/_utils/hft_timeseries_data.py
realized_library/_utils/integral_approximation.py
realized_library/_utils/std_norm_dist_moments.py
realized_library/estimators/__init__.py
realized_library/estimators/jump_detection/abd_test.py
realized_library/estimators/jump_detection/asj_test.py
realized_library/estimators/jump_detection/bns_test.py
realized_library/estimators/jump_detection/jo_test.py
realized_library/estimators/jump_detection/lm_test.py
realized_library/estimators/variance/__init__.py
realized_library/estimators/variance/bipower_variation.py
realized_library/estimators/variance/integrated_variance.py
realized_library/estimators/variance/med_rq.py
realized_library/estimators/variance/med_rv.py
realized_library/estimators/variance/min_rq.py
realized_library/estimators/variance/min_rv.py
realized_library/estimators/variance/modulated_multipower_variation.py
realized_library/estimators/variance/multipower_variation.py
realized_library/estimators/variance/noise_variance.py
realized_library/estimators/variance/realized_kernel.py
realized_library/estimators/variance/realized_variance.py
realized_library/estimators/variance/trucated_multipower_variation.py
realized_library/utils/__init__.py
realized_library/utils/preaverage.py
realized_library/utils/resampling.py
realized_library/utils/statistics_thresholding.py
realized_library/utils/subsampling.py
realized_library-0.1.2.dist-info/licenses/LICENSE
realized_library-0.1.2.dist-info/METADATA
realized_library-0.1.2.dist-info/WHEEL
realized_library-0.1.2.dist-info/top_level.txt
realized_library-0.1.2.dist-info/RECORD
