Metadata-Version: 2.4
Name: realized-library
Version: 0.1.2
Summary: A Python package for high-frequency econometrics estimators
Author-email: Gabin Taibi <gabin.taibi@icloud.com>
License: MIT
Keywords: volatility,finance,high-frequency,jump detection
License-File: LICENSE
Requires-Dist: numba
Requires-Dist: numpy
Requires-Dist: scipy
Requires-Dist: pandas
Requires-Dist: polars
Dynamic: license-file
